{
    "name": "MIT6.5840",
    "image": "mcr.microsoft.com/devcontainers/go:dev-1.22-bookworm",
    "customizations": {
        "vscode": {
            "extensions": [
                "golang.Go"
            ]
        },
        "settings": {
            "go.gopath": "/go",
            "go.goroot": "/usr/local/go",
            "go.toolsGopath": "/go/bin",
            "go.useLanguageServer": true,
            "files.eol": "\n"
        }
    },
    "forwardPorts": [
        8080
    ],
    "remoteUser": "vscode"
}